discard_files/__init__.py
discard_files/messages_router.py
discard_files/read_sheet.py
discard_files/webhook_handlers.py
discard_files/whatsapp_messages.py
src/__init__.py
src/app/__init__.py
src/app/main.py
src/app/routers/__init__.py
src/app/routers/message_router.py
src/app/routers/send_sheet_router.py
src/app/routers/webhook_router.py
src/data_extractors/__init__.py
src/data_extractors/google_services_init.py
src/data_extractors/spreadsheet_reader.py
src/message_handler/__init__.py
src/message_handler/base_message_handler.py
src/message_handler/messenger_message_handler.py
src/message_handler/telegram_message_handler.py
src/message_handler/twilio_message_handler.py
src/message_handler/whatsapp_message_handler.py
src/telegram_sheet/__init__.py
src/telegram_sheet/telegram_client_handler.py
src/telegram_sheet/telegram_sheet_handlers.py
src/twilio_sheet/__init__.py
src/twilio_sheet/twilio_sheet_message.py
src/utils/__init__.py
src/utils/config.py
src/utils/convert_to_downloadable_link.py
src/utils/model.py
src/utils/session_setup.py
src/utils/status_enums.py
src/utils/whats_video_format.py
src/webhook_handler/__init__.py
src/webhook_handler/base_webhook_handler.py
src/webhook_handler/messenger_webhook_handler.py
src/webhook_handler/telegram_webhook_handler.py
src/webhook_handler/twilio_webhook_handler.py
src/webhook_handler/webhook_handler_factory.py
src/webhook_handler/whatsapp_webhook_handler.py
src/whatsapp_sheet/__init__.py
src/whatsapp_sheet/send_sheet_handlers.py
temp_images/__init__.py
tests/__init__.py
tests/test_api.py
tests/test_token_renewal.py
tests/test_webhook_simple.py
tests/test_webhooks.py
tests/test_whatsapp_message.py
tests/test_whatsapp_template.py
lenaai_whatsapp_cloud-0.1.0.dist-info/METADATA
lenaai_whatsapp_cloud-0.1.0.dist-info/WHEEL
lenaai_whatsapp_cloud-0.1.0.dist-info/top_level.txt
lenaai_whatsapp_cloud-0.1.0.dist-info/RECORD
