Metadata-Version: 2.4
Name: lenaai-whatsapp-cloud
Version: 0.1.0
Summary: A library for WhatsApp Cloud and related messaging integrations.
Home-page: 
Author: LenaAI
Author-email: dev@lenaai.net
Classifier: Programming Language :: Python :: 3
Classifier: License :: OSI Approved :: MIT License
Classifier: Operating System :: OS Independent
Requires-Python: >=3.9
Dynamic: author
Dynamic: author-email
Dynamic: classifier
Dynamic: requires-python
Dynamic: summary
